{
 "actions": [],
 "creation": "2026-04-19 10:00:00.000000",
 "doctype": "DocType",
 "editable_grid": 1,
 "engine": "InnoDB",
 "field_order": [
  "posting_date",
  "transaction_type",
  "voucher_type",
  "voucher_no",
  "account",
  "debit",
  "credit",
  "remarks"
 ],
 "fields": [
  {
   "fieldname": "posting_date",
   "fieldtype": "Date",
   "in_list_view": 1,
   "label": "Posting Date",
   "allow_on_submit": 1
  },
  {
   "fieldname": "transaction_type",
   "fieldtype": "Select",
   "in_list_view": 1,
   "label": "Transaction Type",
   "options": "\nMargin Block\nBank Charge\nSupplier Invoice\nSupplier Payment\nBank Paid Supplier\nCompany Settlement\nMargin Release\nAmendment Charge\nOther",
   "allow_on_submit": 1
  },
  {
   "fieldname": "voucher_type",
   "fieldtype": "Link",
   "label": "Voucher Type",
   "options": "DocType",
   "allow_on_submit": 1
  },
  {
   "fieldname": "voucher_no",
   "fieldtype": "Dynamic Link",
   "in_list_view": 1,
   "label": "Voucher No",
   "options": "voucher_type",
   "allow_on_submit": 1
  },
  {
   "fieldname": "account",
   "fieldtype": "Link",
   "in_list_view": 1,
   "label": "Account",
   "options": "Account",
   "allow_on_submit": 1
  },
  {
   "fieldname": "debit",
   "fieldtype": "Currency",
   "in_list_view": 1,
   "label": "Debit",
   "allow_on_submit": 1
  },
  {
   "fieldname": "credit",
   "fieldtype": "Currency",
   "in_list_view": 1,
   "label": "Credit",
   "allow_on_submit": 1
  },
  {
   "fieldname": "remarks",
   "fieldtype": "Data",
   "label": "Remarks",
   "allow_on_submit": 1
  }
 ],
 "istable": 1,
 "links": [],
 "modified": "2026-04-19 10:00:00.000000",
 "modified_by": "Administrator",
 "module": "Printechs LC",
 "name": "LC Voucher Link",
 "owner": "Administrator",
 "permissions": [],
 "sort_field": "modified",
 "sort_order": "DESC",
 "states": []
}
